opal/__init__.py
opal/__main__.py
opal/components/Compiler.py
opal/components/Tokens.py
opal/components/utils.py
opal/examples/2048.opal
opal/examples/fibonacci.opal
opal/examples/fireworks.opal
opal/examples/rain.opal
opal/libs/Array.py
opal/libs/Queue.py
opal/libs/Stack.py
opal/libs/Vector.py
opal/libs/_internals.py
opal/libs/char.py
opal/libs/fastSort.opal
opal/libs/helpers.opal
opal/libs/merge.opal
opal/libs/sort.opal
opal/libs/stableSort.opal
opal/libs/std.opal
opal/libs/graphics/Graphics.py
opal/libs/graphics/icon.png
opal/runner/build.py
opal/runner/icon.ico
opal_lang-2024.5.10.7.dist-info/LICENSE
opal_lang-2024.5.10.7.dist-info/METADATA
opal_lang-2024.5.10.7.dist-info/WHEEL
opal_lang-2024.5.10.7.dist-info/top_level.txt
opal_lang-2024.5.10.7.dist-info/RECORD
