Metadata-Version: 2.1
Name: opal-lang
Version: 2024.5.10.7
Summary: A programming language based on Python and Cython
Project-URL: Homepage, https://github.com/thatsOven/opal-lang
Classifier: Programming Language :: Python :: 3
Classifier: License :: OSI Approved :: MIT License
Classifier: Operating System :: OS Independent
Requires-Python: >=3.11
License-File: LICENSE
Requires-Dist: pyinstaller
Requires-Dist: colorama
Requires-Dist: pygame-ce ==2.3.2
Requires-Dist: numpy
Requires-Dist: typeguard
Requires-Dist: Cython
Requires-Dist: ianthe >=2023.12.17
